{
  "errorCode": 0,
  "reason": "获取成功",
  "data": [
    {
      "name": "Binance-Peg BSC-USD",
      "protocol": "20",
      "symbol": "USDT",
      "address": "0x55d398326f99059ff775485246999027b3197955",
      "decimals": 18,
      "logoURI": "https://static.w3wallet.link/bsc/dapplogo/usdt.png"
    },
    {
      "name": "PG",
      "protocol": "20",
      "symbol": "PG",
      "address": "0x7bb8bb3e4f3f8c40d4ab3ba07622453c8d8cc949",
      "decimals": 18,
      "logoURI": "https://static.w3wallet.link/bsc/dapplogo/pg3.png"
    },
    {
      "name": "OSKDAO",
      "protocol": "20",
      "symbol": "OSKDAO",
      "address": "0x8555af519D6E98612EA22179213C60fD6cbbd7ca",
      "decimals": 18,
      "logoURI": "https://static.w3wallet.link/bsc/dapplogo/oskdao.png"
    },
    {
      "name": "W3",
      "protocol": "20",
      "symbol": "W3",
      "address": "0x9Bac79BC5a0EDe5E1a3A422f6f58Fd764bA7652F",
      "decimals": 18,
      "logoURI": "https://static.w3wallet.link/bsc/dapplogo/w3(2).png"
    },
    {
      "name": "PNS",
      "protocol": "20",
      "symbol": "PNS",
      "address": "0x815c143c26e8739741c037CB6E8Ad771A2B36b4a",
      "decimals": 18,
      "logoURI": "https://static.w3wallet.link/bsc/dapplogo/pns.png"
    },
    {
      "name": "PNN",
      "protocol": "20",
      "symbol": "PNN",
      "address": "0x59a25CB6A4fE264d698ba9a2816C47778280aBbA",
      "decimals": 0,
      "logoURI": "https://static.w3wallet.link/pg(main)/pg/dapplogo/pnn.png"
    },
    {
      "name": "PG",
      "protocol": "20",
      "symbol": "PG",
      "address": "0xf887086664674bde940bA47Cad139CeFeef1b5Ef",
      "decimals": 18,
      "logoURI": "https://static.w3wallet.link/bsc/dapplogo/pg1.png"
    },
    {
      "name": "PG",
      "protocol": "20",
      "symbol": "PG",
      "address": "0xfA82075A6d8F85Be9146e64e0F02BaA849F8E8Fb",
      "decimals": 18,
      "logoURI": "https://static.w3wallet.link/bsc/pg/dapplogo/pg2.png"
    },
    {
      "name": "OSK-DAO",
      "protocol": "20",
      "symbol": "OSK-DAO",
      "address": "0xC5db5aFee4C55DfAD5F2b8226C6ac882E6956a0A",
      "decimals": 18,
      "logoURI": "https://static.w3wallet.link/bsc/dapplogo/osk-dao.png"
    },
    {
      "name": "w3",
      "protocol": "20",
      "symbol": "w3",
      "address": "0x7d6801E8CF716e6a06914b7106578F3beb40e51d",
      "decimals": 18,
      "logoURI": "https://static.w3wallet.link/bsc/dapplogo/w3.png"
    },
    {
      "name": "FogDao Token",
      "protocol": "20",
      "symbol": "FOG",
      "address": "0x079a1e0c6f1eb4912064670255d6084edce4f454",
      "decimals": 18,
      "logoURI": ""
    },
    {
      "name": "MetaPoint",
      "protocol": "20",
      "symbol": "POT",
      "address": "0x3b5e381130673f794a5cf67fbba48688386bea86",
      "decimals": 18,
      "logoURI": ""
    }
  ]
}
