{
 "name": "",
 "website": "https://www.hecochain.com/en-us/",
 "description":"The live Wrapped Huobi Token price today is $2.85 USD with a 24-hour trading volume of $22,704.67 USD. We update our WHT to USD price in real-time. Wrapped Huobi Token is down 0.06% in the last 24 hours. The current CoinMarketCap ranking is #4526, with a live market cap of not available. The circulating supply is not available and the max. supply is not available.",
 "explorer": "",
 "type": "HRC20",
 "symbol": "WHT",
 "decimals": 18,
 "status": "active",
 "id": ""
}
